[
  {
    "id": "2K9yv59e10558629613123829891055862961312382987",
    "code": "2K9yv59e",
    "channel": {
      "channelId": 1055862961312382989,
      "guildId": null,
      "position": null,
      "name": "приветствие-и-правила",
      "topic": null,
      "nsfw": null,
      "lastMessageId": 0,
      "userLimit": null,
      "rateLimitPerUser": null,
      "recipients": null,
      "icon": null,
      "ownerId": null,
      "applicationId": null,
      "parentId": 0,
      "lastPinTimestamp": null,
      "rtcRegion": null
    },
    "inviter": {
      "userId": 694851995852341349,
      "username": "A-Lex",
      "discriminator": "2378",
      "avatar": "75d85af119d9b1b77892746b4227c902",
      "banner": null,
      "bot": null,
      "system": null,
      "mfaEnabled": null,
      "locale": null,
      "verified": null,
      "email": null,
      "flags": null,
      "premiumType": null,
      "publicFlags": null,
      "events": null
    },
    "targetType": null,
    "targetUser": null,
    "approximatePresenceCount": null,
    "approximateMemberCount": null,
    "expiresAt": "2022-12-30T15:31:46+00:00",
    "uses": 0,
    "maxUses": 0,
    "maxAge": 604800,
    "temporary": null,
    "createdAt": "2022-12-23T15:31:46.489000+00:00",
    "utm": null,
    "link": "https://discord.gg/2K9yv59e"
  },
  {
    "id": "BaUUKadX4m10558629613123829891055862961312382987",
    "code": "BaUUKadX4m",
    "channel": {
      "channelId": 1055862961312382989,
      "guildId": null,
      "position": null,
      "name": "приветствие-и-правила",
      "topic": null,
      "nsfw": null,
      "lastMessageId": 0,
      "userLimit": null,
      "rateLimitPerUser": null,
      "recipients": null,
      "icon": null,
      "ownerId": null,
      "applicationId": null,
      "parentId": 0,
      "lastPinTimestamp": null,
      "rtcRegion": null
    },
    "inviter": {
      "userId": 694851995852341349,
      "username": "A-Lex",
      "discriminator": "2378",
      "avatar": "75d85af119d9b1b77892746b4227c902",
      "banner": null,
      "bot": null,
      "system": null,
      "mfaEnabled": null,
      "locale": null,
      "verified": null,
      "email": null,
      "flags": null,
      "premiumType": null,
      "publicFlags": null,
      "events": null
    },
    "targetType": null,
    "targetUser": null,
    "approximatePresenceCount": null,
    "approximateMemberCount": null,
    "expiresAt": null,
    "uses": 13,
    "maxUses": 0,
    "maxAge": 0,
    "temporary": null,
    "createdAt": "2022-12-23T15:32:07.589000+00:00",
    "utm": null,
    "link": "https://discord.gg/BaUUKadX4m"
  },
  {
    "id": "F4QRXMqB10558701196806841051055870119680684102",
    "code": "F4QRXMqB",
    "channel": {
      "channelId": 1055870119680684105,
      "guildId": null,
      "position": null,
      "name": "основной",
      "topic": null,
      "nsfw": null,
      "lastMessageId": 0,
      "userLimit": null,
      "rateLimitPerUser": null,
      "recipients": null,
      "icon": null,
      "ownerId": null,
      "applicationId": null,
      "parentId": 0,
      "lastPinTimestamp": null,
      "rtcRegion": null
    },
    "inviter": {
      "userId": 694851995852341349,
      "username": "A-Lex",
      "discriminator": "2378",
      "avatar": "75d85af119d9b1b77892746b4227c902",
      "banner": null,
      "bot": null,
      "system": null,
      "mfaEnabled": null,
      "locale": null,
      "verified": null,
      "email": null,
      "flags": null,
      "premiumType": null,
      "publicFlags": null,
      "events": null
    },
    "targetType": null,
    "targetUser": null,
    "approximatePresenceCount": null,
    "approximateMemberCount": null,
    "expiresAt": "2023-01-01T21:20:41+00:00",
    "uses": 11,
    "maxUses": 0,
    "maxAge": 604800,
    "temporary": null,
    "createdAt": "2022-12-25T21:20:41.368000+00:00",
    "utm": null,
    "link": "https://discord.gg/F4QRXMqB"
  },
  {
    "id": "9StVnaFY10566471463943578221056647145450647594",
    "code": "9StVnaFY",
    "channel": {
      "channelId": 1056647146394357822,
      "guildId": null,
      "position": null,
      "name": "основной",
      "topic": null,
      "nsfw": null,
      "lastMessageId": 0,
      "userLimit": null,
      "rateLimitPerUser": null,
      "recipients": null,
      "icon": null,
      "ownerId": null,
      "applicationId": null,
      "parentId": 0,
      "lastPinTimestamp": null,
      "rtcRegion": null
    },
    "inviter": {
      "userId": 678962703078916098,
      "username": "introex",
      "discriminator": "9024",
      "avatar": null,
      "banner": null,
      "bot": null,
      "system": null,
      "mfaEnabled": null,
      "locale": null,
      "verified": null,
      "email": null,
      "flags": null,
      "premiumType": null,
      "publicFlags": null,
      "events": null
    },
    "targetType": null,
    "targetUser": null,
    "approximatePresenceCount": null,
    "approximateMemberCount": null,
    "expiresAt": "2023-01-01T19:50:01+00:00",
    "uses": 1,
    "maxUses": 0,
    "maxAge": 604800,
    "temporary": null,
    "createdAt": "2022-12-25T19:50:01.656000+00:00",
    "utm": null,
    "link": "https://discord.gg/9StVnaFY"
  },
  {
    "id": "chJ65eX710558701196806841051055870119680684102",
    "code": "chJ65eX7",
    "channel": {
      "channelId": 1055870119680684105,
      "guildId": null,
      "position": null,
      "name": "основной",
      "topic": null,
      "nsfw": null,
      "lastMessageId": 0,
      "userLimit": null,
      "rateLimitPerUser": null,
      "recipients": null,
      "icon": null,
      "ownerId": null,
      "applicationId": null,
      "parentId": 0,
      "lastPinTimestamp": null,
      "rtcRegion": null
    },
    "inviter": {
      "userId": 1056645412989190195,
      "username": "ii marketing bot",
      "discriminator": "8618",
      "avatar": null,
      "banner": null,
      "bot": true,
      "system": null,
      "mfaEnabled": null,
      "locale": null,
      "verified": null,
      "email": null,
      "flags": null,
      "premiumType": null,
      "publicFlags": null,
      "events": null
    },
    "targetType": null,
    "targetUser": null,
    "approximatePresenceCount": null,
    "approximateMemberCount": null,
    "expiresAt": "2023-01-18T02:11:43+00:00",
    "uses": 0,
    "maxUses": 0,
    "maxAge": 86400,
    "temporary": null,
    "createdAt": "2023-01-17T02:11:43.216000+00:00",
    "utm": null,
    "link": "https://discord.gg/chJ65eX7"
  }
]
